lstr/__init__.py
lstr/amount.py
lstr/lock.py
lstr/lstr.py
lstr/py.typed
lstr/version.py
lstr-1.0.0.dist-info/LICENSE
lstr-1.0.0.dist-info/METADATA
lstr-1.0.0.dist-info/WHEEL
lstr-1.0.0.dist-info/top_level.txt
lstr-1.0.0.dist-info/RECORD
