Metadata-Version: 2.1
Name: lstr
Version: 1.0.0
Summary: Partially lockable strings
Home-page: https://github.com/cariad/lstr
Author: Cariad Eccleston
Author-email: cariad@hey.com
License: MIT License
Platform: UNKNOWN
Classifier: Development Status :: 5 - Production/Stable
Classifier: Intended Audience :: Developers
Classifier: License :: OSI Approved :: MIT License
Classifier: Natural Language :: English
Classifier: Operating System :: OS Independent
Classifier: Programming Language :: Python :: 3 :: Only
Classifier: Programming Language :: Python :: 3.8
Classifier: Programming Language :: Python :: 3.9
Classifier: Typing :: Typed
Requires-Python: >=3.8
